colour_valgrind-0.3.9.dist-info/DESCRIPTION.rst
colour_valgrind-0.3.9.dist-info/METADATA
colour_valgrind-0.3.9.dist-info/RECORD
colour_valgrind-0.3.9.dist-info/WHEEL
colour_valgrind-0.3.9.dist-info/entry_points.txt
colour_valgrind-0.3.9.dist-info/metadata.json
colour_valgrind-0.3.9.dist-info/top_level.txt
colourvalgrind/__init__.py
colourvalgrind/colourvalgrind.py
colourvalgrind/command_line.py
