Metadata-Version: 2.0
Name: colour-valgrind
Version: 0.3.9
Summary: Wraps Valgrind to colour the output.
Home-page: http://github.com/StarlitGhost/colour-valgrind
Author: StarlitGhost
Author-email: starlitwraith@gmail.com
License: MIT
Keywords: valgrind color colour filter
Platform: UNKNOWN
Classifier: Development Status :: 3 - Alpha
Classifier: Environment :: Console
Classifier: Intended Audience :: Developers
Classifier: License :: OSI Approved :: MIT License
Classifier: Programming Language :: Python :: 2.7
Classifier: Programming Language :: Python :: 3
Classifier: Topic :: Software Development :: Debuggers
Classifier: Topic :: Text Processing :: Filters
Classifier: Topic :: Utilities
Requires-Dist: colorama
Requires-Dist: regex
Requires-Dist: six
